tython/__init__.py
tython/definitions.py
tython/src/__init__.py
tython/src/main/__init__.py
tython/src/main/config_reader/__init__.py
tython/src/main/config_reader/config_reader.py
tython/src/main/data_holder/__init__.py
tython/src/main/data_holder/abstract_key.py
tython/src/main/data_holder/data_holder.py
tython/src/main/data_structures/__init__.py
tython/src/main/data_structures/constants.py
tython/src/main/data_structures/dict.py
tython/src/main/data_structures/list.py
tython/src/main/data_structures/placeholder.py
tython/src/main/data_structures/set.py
tython/src/main/nullable/__init__.py
tython/src/main/nullable/nullable.py
tython/src/main/path/__init__.py
tython/src/main/path/path.py
tython/src/main/resources/__init__.py
tython/src/main/resources/config.ini
tython/src/test/__init__.py
tython/src/test/data_structures/__init__.py
tython/src/test/data_structures/test_dict.py
tython/src/test/data_structures/test_list.py
tython/src/test/data_structures/test_set.py
tython/src/test/nullable/__init__.py
tython/src/test/nullable/test_nullable.py
tython/src/test/path/__init__.py
tython/src/test/path/test_path.py
tython/src/test/resources/__init__.py
tython_toolkit-0.0.8.dist-info/LICENSE
tython_toolkit-0.0.8.dist-info/METADATA
tython_toolkit-0.0.8.dist-info/WHEEL
tython_toolkit-0.0.8.dist-info/top_level.txt
tython_toolkit-0.0.8.dist-info/RECORD
