Metadata-Version: 2.1
Name: tython-toolkit
Version: 0.0.8
Summary: Tython goal is to implement cool features from other languages such as Kotlin, into Python.
Home-page: https://github.com/rxonhe/tython
Author: Rafael Choinhet
Author-email: choinhet@gmail.com
License: MIT
Platform: UNKNOWN
Classifier: Programming Language :: Python :: 3
Classifier: License :: OSI Approved :: MIT License
Classifier: Operating System :: OS Independent
Requires-Python: >=3.10
License-File: LICENSE
